{
  "channeldata_version": 1,
  "packages": {
    "graf": {
      "activate.d": false,
      "binary_prefix": false,
      "deactivate.d": false,
      "description": null,
      "dev_url": null,
      "doc_source_url": null,
      "doc_url": null,
      "home": "https://github.com/ncbi/graf",
      "icon_hash": null,
      "icon_url": null,
      "identifiers": null,
      "keywords": null,
      "license": null,
      "post_link": false,
      "pre_link": false,
      "pre_unlink": false,
      "recipe_origin": null,
      "run_exports": {},
      "source_git_url": null,
      "source_url": "https://github.com/ncbi/graf/archive/master.zip",
      "subdirs": [
        "linux-64"
      ],
      "summary": null,
      "tags": null,
      "text_prefix": false,
      "timestamp": 1610563524,
      "version": "12sep2018"
    },
    "initialize_output_directories": {
      "activate.d": false,
      "binary_prefix": true,
      "deactivate.d": false,
      "description": null,
      "dev_url": "https://github.com/NCI-CGR/initialize_output_directories",
      "doc_source_url": null,
      "doc_url": null,
      "home": "https://github.com/NCI-CGR/initialize_output_directories",
      "icon_hash": null,
      "icon_url": null,
      "identifiers": null,
      "keywords": null,
      "license": "MIT",
      "post_link": false,
      "pre_link": false,
      "pre_unlink": false,
      "recipe_origin": null,
      "run_exports": {},
      "source_git_url": "https://github.com/NCI-CGR/initialize_output_directories.git",
      "source_url": null,
      "subdirs": [
        "linux-64"
      ],
      "summary": "preprocessing module for \"plco-analysis\" pipeline",
      "tags": null,
      "text_prefix": false,
      "timestamp": 1610564079,
      "version": "v1.0.4"
    }
  },
  "subdirs": [
    "linux-64",
    "noarch"
  ]
}
